Metadata-Version: 2.1
Name: textpackf
Version: 0.0.5
Summary: Quickly identify and group similar text strings in a large dataset
Home-page: https://github.com/lukewhyte/textpack
Author: Luke Whyte
Author-email: lukeawhyte@gmail.com
License: UNKNOWN
Platform: UNKNOWN
Classifier: Programming Language :: Python :: 3
Classifier: License :: OSI Approved :: MIT License
Classifier: Operating System :: OS Independent
